hybrid_pool_executor/__init__.py
hybrid_pool_executor/base.py
hybrid_pool_executor/constants.py
hybrid_pool_executor/executor.py
hybrid_pool_executor/spec.py
hybrid_pool_executor/utils.py
hybrid_pool_executor/workers/__init__.py
hybrid_pool_executor/workers/asyncio/__init__.py
hybrid_pool_executor/workers/asyncio/manager.py
hybrid_pool_executor/workers/asyncio/worker.py
hybrid_pool_executor/workers/process/__init__.py
hybrid_pool_executor/workers/process/manager.py
hybrid_pool_executor/workers/process/queue.py
hybrid_pool_executor/workers/process/worker.py
hybrid_pool_executor/workers/thread/__init__.py
hybrid_pool_executor/workers/thread/manager.py
hybrid_pool_executor/workers/thread/worker.py
hybrid_pool_executor-0.0.4.dist-info/LICENSE
hybrid_pool_executor-0.0.4.dist-info/METADATA
hybrid_pool_executor-0.0.4.dist-info/WHEEL
hybrid_pool_executor-0.0.4.dist-info/top_level.txt
hybrid_pool_executor-0.0.4.dist-info/RECORD
